{"cameraMode":{"drawMode":0,"name":"Shaded","section":"Shading Mode"},"sceneLighting":false,"audioPlay":false,"sceneViewState":{"showFog":true,"showMaterialUpdate":false,"showSkybox":false,"showFlares":true,"showImageEffects":true,"showParticleSystems":true},"in2DMode":false,"pivot":{"x":-1.4970521926879883,"y":2.802281618118286,"z":-0.34201720356941225},"rotation":{"x":0.012703564949333668,"y":-0.7200227975845337,"z":0.013184117153286934,"w":0.6937139630317688},"size":2.439175605773926,"orthographic":false}