{"cameraMode":{"drawMode":0,"name":"Shaded","section":"Shading Mode"},"sceneLighting":false,"audioPlay":false,"sceneViewState":{"showFog":true,"showMaterialUpdate":false,"showSkybox":false,"showFlares":true,"showImageEffects":true,"showParticleSystems":true},"in2DMode":false,"pivot":{"x":-3.6880314350128176,"y":0.7251188158988953,"z":1.087586522102356},"rotation":{"x":-0.05695287138223648,"y":0.5917754769325256,"z":-0.04197786748409271,"w":-0.8030056357383728},"size":4.580174922943115,"orthographic":false}